discord_surveys/__init__.py
discord_surveys/survey.py
discord_surveys-1.0.11.dist-info/LICENSE
discord_surveys-1.0.11.dist-info/METADATA
discord_surveys-1.0.11.dist-info/WHEEL
discord_surveys-1.0.11.dist-info/top_level.txt
discord_surveys-1.0.11.dist-info/RECORD
