Metadata-Version: 2.1
Name: discord-surveys
Version: 1.0.11
Summary: A survey object that utilizes discord.py and discord-interactions.
Home-page: https://github.com/refekt/discord-surveys
Author: refekt
Author-email: refekt@gmail.com
License: MIT
Platform: UNKNOWN
Classifier: Programming Language :: Python :: 3
Classifier: License :: OSI Approved :: MIT License
Classifier: Operating System :: OS Independent
Requires-Python: >=3.7.0
License-File: LICENSE
Requires-Dist: discord-py-interactions
Requires-Dist: discord.py
